XStatic_Dagre_D3-0.4.17.0-py3.7-nspkg.pth
xstatic/pkg/dagre_d3/__init__.py
xstatic/pkg/dagre_d3/data/dagre-d3.core.js
xstatic/pkg/dagre_d3/data/dagre-d3.core.min.js
xstatic/pkg/dagre_d3/data/dagre-d3.js
xstatic/pkg/dagre_d3/data/dagre-d3.min.js
XStatic_Dagre_D3-0.4.17.0.dist-info/METADATA
XStatic_Dagre_D3-0.4.17.0.dist-info/WHEEL
XStatic_Dagre_D3-0.4.17.0.dist-info/namespace_packages.txt
XStatic_Dagre_D3-0.4.17.0.dist-info/top_level.txt
XStatic_Dagre_D3-0.4.17.0.dist-info/RECORD
