Metadata-Version: 2.1
Name: XStatic-Dagre-D3
Version: 0.4.17.0
Summary: Dagre-D3 0.4.17 (XStatic packaging standard)
Home-page: https://github.com/dagrejs/dagre-d3
Maintainer: Michal Arbet
Maintainer-email: michal.arbet@ultimum.io
License: (same as Dagre-D3)
Keywords: dagre_d3 xstatic
Platform: any
